rbf-2.1.1.dist-info/DESCRIPTION.rst
rbf-2.1.1.dist-info/METADATA
rbf-2.1.1.dist-info/RECORD
rbf-2.1.1.dist-info/WHEEL
rbf-2.1.1.dist-info/entry_points.txt
rbf-2.1.1.dist-info/metadata.json
rbf-2.1.1.dist-info/top_level.txt
rbfDB/__init__.py
rbfDB/assertion.py
rbfDB/connection_manager.py
rbfDB/query.py
rbfDB/version.py
rbfDataDriver/__init__.py
rbfDataDriver/csvreader.py
rbfDataDriver/pictreader.py
rbfDataDriver/rbfDataDriver.py
rbfDataDriver/version.py
rbfDataDriver/xlsreader.py
rbfDesktop/__init__.py
rbfDesktop/version.py
rbfDesktop/bin/Castle.Core.dll
rbfDesktop/bin/TestStack.White.Reporting.dll
rbfDesktop/bin/TestStack.White.ScreenObjects.dll
rbfDesktop/bin/TestStack.White.dll
rbfDesktop/keywords/__init__.py
rbfDesktop/keywords/application.py
rbfDesktop/keywords/configuration.py
rbfDesktop/keywords/keyboard.py
rbfDesktop/keywords/librarycomponent.py
rbfDesktop/keywords/robotlibcore.py
rbfDesktop/keywords/screenshot.py
rbfDesktop/keywords/window.py
rbfDesktop/keywords/items/__init__.py
rbfDesktop/keywords/items/buttons.py
rbfDesktop/keywords/items/label.py
rbfDesktop/keywords/items/listcontrols.py
rbfDesktop/keywords/items/listview.py
rbfDesktop/keywords/items/menu.py
rbfDesktop/keywords/items/mouse.py
rbfDesktop/keywords/items/progressbar.py
rbfDesktop/keywords/items/slider.py
rbfDesktop/keywords/items/tab.py
rbfDesktop/keywords/items/textbox.py
rbfDesktop/keywords/items/tree.py
rbfDesktop/keywords/items/uiitem.py
rbfDesktop/utils/__init__.py
rbfDesktop/utils/click.py
rbfExcel/__init__.py
rbfExcel/base.py
rbfExcel/reader.py
rbfExcel/utils.py
rbfExcel/version.py
rbfExcel/writer.py
rbfFTP/__init__.py
rbfFTP/rbfFTP.py
rbfFTP/version.py
rbfHTTP/RequestsKeywords.py
rbfHTTP/__init__.py
rbfHTTP/compat.py
rbfHTTP/version.py
rbfMetrics/__init__.py
rbfMetrics/keyword_results.py
rbfMetrics/keyword_stats.py
rbfMetrics/robotmetrics.py
rbfMetrics/runner.py
rbfMetrics/suite_results.py
rbfMetrics/test_results.py
rbfMetrics/test_stats.py
rbfMetrics/version.py
rbfMobile/__init__.py
rbfMobile/version.py
rbfMobile/keywords/__init__.py
rbfMobile/keywords/_android_utils.py
rbfMobile/keywords/_applicationmanagement.py
